leximpact_prepare_data/__init__.py
leximpact_prepare_data/pipeline_leximpact.ipynb
leximpact_prepare_data/pipeline_survey_scenario.py
leximpact_prepare_data/pipeline_tax_and_benefit_system.py
leximpact_prepare_data/scenario_tools/__init__.py
leximpact_prepare_data/scenario_tools/calib_and_copules.py
leximpact_prepare_data/scenario_tools/comparison.py
leximpact_prepare_data/scenario_tools/helpers_survey_scenario.py
leximpact_prepare_data/scenario_tools/imputation_erfs.py
leximpact_prepare_data/scenario_tools/input_data_builder.py
leximpact_prepare_data/scenario_tools/monte_carlo_computer.py
leximpact_prepare_data-0.1.3.dist-info/LICENSE
leximpact_prepare_data-0.1.3.dist-info/LICENSE.md
leximpact_prepare_data-0.1.3.dist-info/METADATA
leximpact_prepare_data-0.1.3.dist-info/WHEEL
leximpact_prepare_data-0.1.3.dist-info/entry_points.txt
leximpact_prepare_data-0.1.3.dist-info/RECORD
