Metadata-Version: 2.1
Name: leximpact_prepare_data
Version: 0.1.3
Summary: Prepare data for LexImpact
Home-page: https://leximpact.an.fr/
License: AGPL-3.0
Author: LexImpact
Author-email: leximpact@an.fr
Requires-Python: >=3.10,<4.0
Classifier: License :: OSI Approved :: GNU Affero General Public License v3
Classifier: Programming Language :: Python :: 3
Classifier: Programming Language :: Python :: 3.10
Classifier: Programming Language :: Python :: 3.11
Classifier: Programming Language :: Python :: 3.12
Provides-Extra: pipeline
Requires-Dist: diagrams (>=0.20.0,<0.21.0) ; extra == "pipeline"
Requires-Dist: dtale (>=3.3.0,<4.0.0)
Requires-Dist: ipdb (>=0.13.13,<0.14.0)
Requires-Dist: itsdangerous (==2.0.1)
Requires-Dist: kaleido (==0.2.1)
Requires-Dist: leximpact-aggregates (>=0.0.28,<0.0.29)
Requires-Dist: leximpact-common-python-libraries (>=0.1.1,<0.2.0)
Requires-Dist: leximpact-survey-scenario (>=1.0.1,<2.0.0)
Requires-Dist: markupsafe (==2.0.1)
Requires-Dist: multipledispatch (>=0.6.0,<0.7.0)
Requires-Dist: nbdev (>=2.2.10,<3.0.0)
Requires-Dist: numexpr (==2.8.4)
Requires-Dist: openfisca-survey-manager (>=2.0.0,<3.0.0)
Requires-Dist: pandas (>=2.0.3,<3.0)
Requires-Dist: pip (>=23.2,<24.0)
Requires-Dist: pyarrow (==6.0.1)
Requires-Dist: pydantic (>=1.10.8,<2.0.0)
Requires-Dist: pypandoc (>=1.11,<2.0)
Requires-Dist: python-dotenv (>=0.19.2,<0.20.0) ; extra == "pipeline"
Requires-Dist: scikit-learn (>=1.0.1,<2.0.0) ; extra == "pipeline"
Requires-Dist: tables (>=3.6.1,<4.0.0) ; extra == "pipeline"
Requires-Dist: vaex-core (>=4.8.0,<5.0.0) ; extra == "pipeline"
Requires-Dist: vaex-jupyter (>=0.7.0,<0.8.0)
Requires-Dist: vaex-server (>=0.8.1,<0.9.0)
Requires-Dist: werkzeug (==2.0.1)
Project-URL: Repository, https://git.leximpact.dev/leximpact/leximpact-prepare-data
